Metadata-Version: 2.1
Name: wavedrom
Version: 2.0.3.post3
Summary: WaveDrom compatible python command line
Home-page: https://github.com/wallento/wavedrompy
Author: Aliaksei Chapyzhenka, BreizhGeek, Kazuki Yamamoto, Stefan Wallentowitz
Author-email: k4zuki@github.com, stefan@wallentowitz.de
Keywords: wavedrom svg
Classifier: Development Status :: 4 - Beta
Classifier: Intended Audience :: Developers
Classifier: Topic :: Software Development :: Build Tools
Classifier: License :: OSI Approved :: MIT License
Classifier: Programming Language :: Python :: 2
Classifier: Programming Language :: Python :: 2.7
Classifier: Programming Language :: Python :: 3
Classifier: Programming Language :: Python :: 3.3
Classifier: Programming Language :: Python :: 3.4
Classifier: Programming Language :: Python :: 3.5
Classifier: Programming Language :: Python :: 3.6
Classifier: Programming Language :: Python :: 3.7
Provides-Extra: test
License-File: LICENSE
